dentsu_pkgs/__init__.py
dentsu_pkgs/aws_helpers.py
dentsu_pkgs/glue_helpers.py
dentsu_pkgs/googleads_helpers.py
dentsu_pkgs/misc_helpers.py
dentsu_pkgs-0.3.5.dist-info/LICENSE
dentsu_pkgs-0.3.5.dist-info/METADATA
dentsu_pkgs-0.3.5.dist-info/WHEEL
dentsu_pkgs-0.3.5.dist-info/top_level.txt
dentsu_pkgs-0.3.5.dist-info/RECORD
