Metadata-Version: 2.1
Name: dentsu-pkgs
Version: 0.3.5
Summary: A python library of helper functions for dentsu's cloud solutions.
Home-page: https://github.com/dentsu-inc/dentsu-pkgs
Author: dentsu data labs
Author-email: data.mexico@dentsu.com
License: UNKNOWN
Platform: UNKNOWN
Classifier: Programming Language :: Python :: 3
Classifier: License :: OSI Approved :: MIT License
Classifier: Operating System :: OS Independent
Requires-Python: >=3.6
